zdktestpac/__init__.py
zdktestpac/gbm.py
zdktestpac/hxmt.py
zdktestpac/mccf.py
zdktestpac-0.0.5.dist-info/LICENSE
zdktestpac-0.0.5.dist-info/METADATA
zdktestpac-0.0.5.dist-info/WHEEL
zdktestpac-0.0.5.dist-info/top_level.txt
zdktestpac-0.0.5.dist-info/RECORD
